speakeasy/__init__.py
speakeasy/__main__.py
speakeasy/binemu.py
speakeasy/cli.py
speakeasy/common.py
speakeasy/config_schema.json
speakeasy/const.py
speakeasy/errors.py
speakeasy/memmgr.py
speakeasy/profiler.py
speakeasy/speakeasy.py
speakeasy/struct.py
speakeasy/version.py
speakeasy/configs/default.json
speakeasy/configs/win10_basic_analysis.json
speakeasy/configs/win10_full_analysis.json
speakeasy/configs/win7_full_analysis.json
speakeasy/engines/__init__.py
speakeasy/engines/unicorn_eng.py
speakeasy/resources/files/default.bin
speakeasy/resources/web/decoy.gif
speakeasy/resources/web/decoy.jpg
speakeasy/resources/web/default.bin
speakeasy/resources/web/stager.bin
speakeasy/windows/__init__.py
speakeasy/windows/com.py
speakeasy/windows/common.py
speakeasy/windows/cryptman.py
speakeasy/windows/driveman.py
speakeasy/windows/fileman.py
speakeasy/windows/hammer.py
speakeasy/windows/ioman.py
speakeasy/windows/kernel.py
speakeasy/windows/netman.py
speakeasy/windows/objman.py
speakeasy/windows/regman.py
speakeasy/windows/sessman.py
speakeasy/windows/win32.py
speakeasy/windows/winemu.py
speakeasy/windows/kernel_mods/__init__.py
speakeasy/windows/kernel_mods/kernel_mod.py
speakeasy/windows/kernel_mods/volmgr.py
speakeasy/winenv/__init__.py
speakeasy/winenv/arch.py
speakeasy/winenv/api/__init__.py
speakeasy/winenv/api/api.py
speakeasy/winenv/api/winapi.py
speakeasy/winenv/api/kernelmode/__init__.py
speakeasy/winenv/api/kernelmode/fwpkclnt.py
speakeasy/winenv/api/kernelmode/hal.py
speakeasy/winenv/api/kernelmode/ndis.py
speakeasy/winenv/api/kernelmode/netio.py
speakeasy/winenv/api/kernelmode/ntoskrnl.py
speakeasy/winenv/api/kernelmode/usbd.py
speakeasy/winenv/api/kernelmode/wdfldr.py
speakeasy/winenv/api/usermode/__init__.py
speakeasy/winenv/api/usermode/advapi32.py
speakeasy/winenv/api/usermode/advpack.py
speakeasy/winenv/api/usermode/bcrypt.py
speakeasy/winenv/api/usermode/com_api.py
speakeasy/winenv/api/usermode/comctl32.py
speakeasy/winenv/api/usermode/crypt32.py
speakeasy_emulator_refined-1.6.1b0.post3.dist-info/LICENSE.txt
speakeasy_emulator_refined-1.6.1b0.post3.dist-info/METADATA
speakeasy_emulator_refined-1.6.1b0.post3.dist-info/WHEEL
speakeasy_emulator_refined-1.6.1b0.post3.dist-info/entry_points.txt
speakeasy_emulator_refined-1.6.1b0.post3.dist-info/top_level.txt
speakeasy_emulator_refined-1.6.1b0.post3.dist-info/RECORD
