Metadata-Version: 2.1
Name: speakeasy-emulator-refined
Version: 1.6.1b0.post3
Summary: Speakeasy malware emulation framework
Home-page: https://github.com/binref/speakeasy
Author: Andrew Davis
License: UNKNOWN
Platform: UNKNOWN
Classifier: Programming Language :: Python :: 3
Classifier: License :: OSI Approved :: MIT License
Classifier: Operating System :: OS Independent
Requires-Python: >=3.6
Requires-Dist: pefile
Requires-Dist: capstone
Requires-Dist: lznt1
Requires-Dist: unicorn
Requires-Dist: jsonschema
Requires-Dist: pycryptodome
